gpuctypes/cuda.py
gpuctypes/hip.py
gpuctypes/opencl.py
gpuctypes-0.2.0.dist-info/METADATA
gpuctypes-0.2.0.dist-info/WHEEL
gpuctypes-0.2.0.dist-info/top_level.txt
gpuctypes-0.2.0.dist-info/RECORD
